tb/__init__.py
tb/api.py
tb/datasource.py
tb/logger.py
tb/utils.py
tb/a/__init__.py
tb/a/api.py
tb/a/datasource.py
tb/litellm/__init__.py
tb/litellm/handler.py
tinybird_python_sdk-0.3.7.dist-info/licenses/LICENSE
tinybird_python_sdk-0.3.7.dist-info/METADATA
tinybird_python_sdk-0.3.7.dist-info/WHEEL
tinybird_python_sdk-0.3.7.dist-info/top_level.txt
tinybird_python_sdk-0.3.7.dist-info/RECORD
