Metadata-Version: 2.4
Name: tinybird-python-sdk
Version: 0.3.7
Summary: Python SDK for Tinybird
Author-email: "tinybird.co" <support@tinybird.co>
Project-URL: homepage, https://github.com/tinybirdco/tinybird-python-sdk
License-File: LICENSE
Requires-Dist: requests~=2.32
Requires-Dist: aiohttp~=3.10
Requires-Dist: backoff~=2.2
Provides-Extra: ai
Requires-Dist: litellm>=1.62.1; extra == "ai"
Dynamic: license-file
